02_sequential_basics/util.svh
`define PB(x) x
`define PD(x) x

02_sequential_basics/02_04_serial_adder_with_vld/02_04_serial_adder_with_vld.sv
//----------------------------------------------------------------------------
// Task
//----------------------------------------------------------------------------

module serial_adder_with_vld
(
  input  clk,
  input  rst,
  input  vld,
  input  a,
  input  b,
  input  last,
  output sum
);

  // Task:
  // Implement a module that performs serial addition of two numbers
  // (one pair of bits is summed per clock cycle).
  //
  // It should have input signals a and b, and output signal sum.
  // Additionally, the module have two control signals, vld and last.
  //
  // The vld signal indicates when the input values are valid.
  // The last signal indicates when the last digits of the input numbers has been received.
  //
  // When vld is high, the module should add the values of a and b and produce the sum.
  // When last is high, the module should output the sum and reset its internal state, but
  // only if vld is also high, otherwise last should be ignored.
  //
  // When rst is high, the module should reset its internal state.

  logic sum;
  logic carry;

  always_comb begin
    sum = '0;
    if (vld)
      sum = a ^ b ^ carry;
  end

  always_ff @(posedge clk)
    if (rst)
      carry <= '0;
    else if (vld)
      if (last)
        carry <= '0;
      else
        carry <= (a & b) | (carry & (a ^ b));

endmodule

02_sequential_basics/02_04_serial_adder_with_vld/testbench.sv
`include "util.svh"

module testbench;

  logic clk;

  initial
  begin
    clk = '0;

    forever
      # 500 clk = ~ clk;
  end

  logic rst;

  initial
  begin
    rst <= 'x;
    repeat (2) @ (posedge clk);
    rst <= '1;
    repeat (2) @ (posedge clk);
    rst <= '0;
  end

  logic vld, a, b, last, actual;
  serial_adder_with_vld sav (.sum (actual), .*);

  localparam n = 128;

  // `define GENERATE

  `ifdef GENERATE

    logic [n - 1:0] seq_vld;
    logic [n - 1:0] seq_a;
    logic [n - 1:0] seq_b;
    logic [n - 1:0] seq_last;

    // Expected sequence of correct output values
    logic [n - 1:0] expected;

    initial
    begin
      @ (negedge rst);

      for (int i = 0; i < n; i ++)
      begin
        { vld, a, b, last } <= $urandom ();

        @ (posedge clk);

        { seq_vld [i], seq_a [i], seq_b [i], seq_last [i], expected [i] }
          = { vld, a, b, last, actual };
      end

      $display ("%b %b %b %b %b",
        seq_vld, seq_a, seq_b, seq_last, expected);

      $finish;
    end

  //--------------------------------------------------------------------------

  `else

    // Sequence of input values
    // localparam [n - 1:0] seq_vld     = 16'b1110_0001_1111_0110;
    // localparam [n - 1:0] seq_a       = 16'b0110_1001_1001_0010;
    // localparam [n - 1:0] seq_b       = 16'b0110_1001_0101_0100;
    // localparam [n - 1:0] seq_last    = 16'b0100_1010_1000_0100;
    //
    // // Expected sequence of correct output values
    // localparam [n - 1:0] expected = 16'b0110_0010_1110_0110;

    localparam [n - 1:0] seq_vld  = 128'b01100111101001010001110111111001111010101000011111011110100111100111100111101011101110010100110010011101101000100111101000110100;
    localparam [n - 1:0] seq_a    = 128'b10111010010111010010111001000101011011001101000011101110001100110001111000000010001110100101100000111110101011011011111001110001;
    localparam [n - 1:0] seq_b    = 128'b00100100111101111111011011010011001101010101000101101101000111100110111100001101111011011011010011000000111110101000010010001000;
    localparam [n - 1:0] seq_last = 128'b01111011001101111100000001110111110011000011011101101100111001111100000110010000011100111110100001111010001011010101101101111110;

    // Expected sequence of correct output values
    localparam [n - 1:0] expected = 128'b10011110101010110010000010010110000110011000000110000011110011010000000100001111110001111110110011111111010101110011101011111001;

    initial
    begin
      `ifdef __ICARUS__
        // Uncomment the following line
        // to generate a VCD file and analyze it using GTKwave or Surfer

        $dumpvars;
      `endif

      @ (negedge rst);

      for (int i = 0; i < n; i ++)
      begin
        vld  <= seq_vld  [i];
        a    <= seq_a    [i];
        b    <= seq_b    [i];
        last <= seq_last [i];

        @ (posedge clk);

        if (vld) begin
          if (actual !== expected[i])
          begin
            $display("FAIL %s", `__FILE__);
            $display("++ INPUT    => {%s, %s, %s, %s, %s}",
                     `PD(i), `PB(vld), `PB(last), `PB(a), `PB(b));
            $display("++ TEST     => {%s, %s}",
                     `PB(expected[i]), `PB(actual));
            $finish(1);
          end
        end
      end

      $display ("PASS %s", `__FILE__);
      $finish;
    end

  `endif

endmodule

02_sequential_basics/02_04_serial_adder_with_vld/dump.vcd
$date
	Tue Jul 21 20:04:48 2026
$end
$version
	Icarus Verilog
$end
$timescale
	1s
$end
$scope module testbench $end
$var wire 1 ! actual $end
$var parameter 128 " expected $end
$var parameter 32 # n $end
$var parameter 128 $ seq_a $end
$var parameter 128 % seq_b $end
$var parameter 128 & seq_last $end
$var parameter 128 ' seq_vld $end
$var reg 1 ( a $end
$var reg 1 ) b $end
$var reg 1 * clk $end
$var reg 1 + last $end
$var reg 1 , rst $end
$var reg 1 - vld $end
$scope module sav $end
$var wire 1 ( a $end
$var wire 1 ) b $end
$var wire 1 * clk $end
$var wire 1 + last $end
$var wire 1 , rst $end
$var wire 1 - vld $end
$var reg 1 . carry $end
$var reg 1 ! sum $end
$upscope $end
$scope begin $ivl_for_loop0 $end
$var integer 32 / i [31:0] $end
$upscope $end
$upscope $end
$enddefinitions $end
$comment Show the parameter values. $end
$dumpall
b1100111101001010001110111111001111010101000011111011110100111100111100111101011101110010100110010011101101000100111101000110100 '
b1111011001101111100000001110111110011000011011101101100111001111100000110010000011100111110100001111010001011010101101101111110 &
b100100111101111111011011010011001101010101000101101101000111100110111100001101111011011011010011000000111110101000010010001000 %
b10111010010111010010111001000101011011001101000011101110001100110001111000000010001110100101100000111110101011011011111001110001 $
b10000000 #
b10011110101010110010000010010110000110011000000110000011110011010000000100001111110001111110110011111111010101110011101011111001 "
$end
#0
$dumpvars
b0 /
x.
x-
x,
x+
0*
x)
x(
0!
$end
#500
1*
#1000
0*
#1500
1,
1*
#2000
0*
#2500
0.
1*
#3000
0*
#3500
0+
0)
1(
0-
0,
1*
#4000
0*
#4500
1+
0(
b1 /
1*
#5000
0*
#5500
1-
b10 /
1*
#6000
0*
#6500
1)
0-
b11 /
1*
#7000
0*
#7500
1!
0)
1(
1-
b100 /
1*
#8000
0*
#8500
b101 /
1*
#9000
0*
#9500
0!
0-
b110 /
1*
#10000
0*
#10500
0+
1)
0(
b111 /
1*
#11000
0*
#11500
1+
0)
b1000 /
1*
#12000
0*
#12500
1!
1(
1-
b1001 /
1*
#13000
0*
#13500
0!
0+
1)
0-
b1010 /
1*
#14000
0*
#14500
1!
1+
0)
1-
b1011 /
1*
#15000
0*
#15500
b1100 /
1*
#16000
0*
#16500
0+
b1101 /
1*
#17000
0*
#17500
0!
1+
0(
b1110 /
1*
#18000
0*
#18500
0+
1)
1(
0-
b1111 /
1*
#19000
0*
#19500
1+
0)
b10000 /
1*
#20000
0*
#20500
1!
0+
1)
0(
1-
b10001 /
1*
#21000
0*
#21500
0!
1+
0)
1(
0-
b10010 /
1*
#22000
0*
#22500
1)
b10011 /
1*
#23000
0*
#23500
0+
0(
b10100 /
1*
#24000
0*
#24500
1+
1(
1-
b10101 /
1*
#25000
0*
#25500
0+
0(
0-
b10110 /
1*
#26000
0*
#26500
1(
1-
b10111 /
1*
#27000
0*
#27500
1!
0)
0(
1.
b11000 /
1*
#28000
0*
#28500
0!
0.
1+
1(
0-
b11001 /
1*
#29000
0*
#29500
1!
0+
1-
b11010 /
1*
#30000
0*
#30500
1+
b11011 /
1*
#31000
0*
#31500
b11100 /
1*
#32000
0*
#32500
0!
0-
b11101 /
1*
#33000
0*
#33500
1)
0(
b11110 /
1*
#34000
0*
#34500
1!
0+
1-
b11111 /
1*
#35000
0*
#35500
0!
0)
0-
b100000 /
1*
#36000
0*
#36500
b100001 /
1*
#37000
0*
#37500
1!
1)
1-
b100010 /
1*
#38000
0*
#38500
1!
1+
0)
1(
b100011 /
1*
#39000
0*
#39500
0!
0+
1)
0-
b100100 /
1*
#40000
0*
#40500
1+
0(
b100101 /
1*
#41000
0*
#41500
1!
0)
1(
1-
b100110 /
1*
#42000
0*
#42500
0!
1)
0(
0-
b100111 /
1*
#43000
0*
#43500
1!
1-
b101000 /
1*
#44000
0*
#44500
0!
0)
1(
0-
b101001 /
1*
#45000
0*
#45500
0+
1)
0(
b101010 /
1*
#46000
0*
#46500
1(
1-
b101011 /
1*
#47000
0*
#47500
1+
0)
1.
b101100 /
1*
#48000
0*
#48500
0.
1)
b101101 /
1*
#49000
0*
#49500
0(
0-
b101110 /
1*
#50000
0*
#50500
1!
0+
1-
b101111 /
1*
#51000
0*
#51500
b110000 /
1*
#52000
0*
#52500
1!
0)
1(
b110001 /
1*
#53000
0*
#53500
0!
1)
0(
0-
b110010 /
1*
#54000
0*
#54500
1!
1-
b110011 /
1*
#55000
0*
#55500
0!
1+
0)
0-
b110100 /
1*
#56000
0*
#56500
0+
1-
b110101 /
1*
#57000
0*
#57500
b110110 /
1*
#58000
0*
#58500
1+
b110111 /
1*
#59000
0*
#59500
1!
1)
b111000 /
1*
#60000
0*
#60500
0!
0+
1(
0-
b111001 /
1*
#61000
0*
#61500
b111010 /
1*
#62000
0*
#62500
1-
b111011 /
1*
#63000
0*
#63500
0)
1.
b111100 /
1*
#64000
0*
#64500
1)
0(
b111101 /
1*
#65000
0*
#65500
1+
b111110 /
1*
#66000
0*
#66500
0.
0)
0-
b111111 /
1*
#67000
0*
#67500
1(
b1000000 /
1*
#68000
0*
#68500
1)
1-
b1000001 /
1*
#69000
0*
#69500
1!
0(
b1000010 /
1*
#70000
0*
#70500
0+
b1000011 /
1*
#71000
0*
#71500
0!
1(
b1000100 /
1*
#72000
0*
#72500
1.
1+
0)
0-
b1000101 /
1*
#73000
0*
#73500
0(
b1000110 /
1*
#74000
0*
#74500
1!
1-
b1000111 /
1*
#75000
0*
#75500
0!
0+
1)
0-
0.
b1001000 /
1*
#76000
0*
#76500
1!
0)
1(
1-
b1001001 /
1*
#77000
0*
#77500
0!
1+
1)
b1001010 /
1*
#78000
0*
#78500
b1001011 /
1*
#79000
0*
#79500
0+
0)
0(
b1001100 /
1*
#80000
0*
#80500
1+
1)
1(
0-
b1001101 /
1*
#81000
0*
#81500
1-
b1001110 /
1*
#82000
0*
#82500
1!
0+
0)
b1001111 /
1*
#83000
0*
#83500
1!
1+
1)
0(
b1010000 /
1*
#84000
0*
#84500
0!
0)
b1010001 /
1*
#85000
0*
#85500
b1010010 /
1*
#86000
0*
#86500
0+
0-
b1010011 /
1*
#87000
0*
#87500
1+
1)
1(
b1010100 /
1*
#88000
0*
#88500
0)
0(
b1010101 /
1*
#89000
0*
#89500
0+
1)
1(
b1010110 /
1*
#90000
0*
#90500
1!
0)
1-
b1010111 /
1*
#91000
0*
#91500
0!
1)
0(
0-
b1011000 /
1*
#92000
0*
#92500
0)
1-
b1011001 /
1*
#93000
0*
#93500
1+
1)
1(
0-
b1011010 /
1*
#94000
0*
#94500
1!
0)
1-
b1011011 /
1*
#95000
0*
#95500
0!
0+
1)
0(
0-
b1011100 /
1*
#96000
0*
#96500
1(
1-
b1011101 /
1*
#97000
0*
#97500
1+
0)
1.
b1011110 /
1*
#98000
0*
#98500
0.
0(
b1011111 /
1*
#99000
0*
#99500
1)
1(
b1100000 /
1*
#100000
0*
#100500
0(
0-
b1100001 /
1*
#101000
0*
#101500
0)
1(
b1100010 /
1*
#102000
0*
#102500
0+
0(
1-
b1100011 /
1*
#103000
0*
#103500
1!
1+
1)
b1100100 /
1*
#104000
0*
#104500
0!
0)
b1100101 /
1*
#105000
0*
#105500
1)
1(
b1100110 /
1*
#106000
0*
#106500
1!
0+
0(
b1100111 /
1*
#107000
0*
#107500
0!
0)
b1101000 /
1*
#108000
0*
#108500
1)
1(
0-
b1101001 /
1*
#109000
0*
#109500
1-
b1101010 /
1*
#110000
0*
#110500
1.
0)
b1101011 /
1*
#111000
0*
#111500
1)
0(
b1101100 /
1*
#112000
0*
#112500
1(
0-
b1101101 /
1*
#113000
0*
#113500
1+
0(
b1101110 /
1*
#114000
0*
#114500
b1101111 /
1*
#115000
0*
#115500
1!
1(
1-
b1110000 /
1*
#116000
0*
#116500
0!
0.
0(
0-
b1110001 /
1*
#117000
0*
#117500
1(
1-
b1110010 /
1*
#118000
0*
#118500
0+
0)
0-
b1110011 /
1*
#119000
0*
#119500
1+
1)
b1110100 /
1*
#120000
0*
#120500
1!
0(
1-
b1110101 /
1*
#121000
0*
#121500
0!
0+
1(
0-
b1110110 /
1*
#122000
0*
#122500
1!
0(
1-
b1110111 /
1*
#123000
0*
#123500
0!
1+
0)
b1111000 /
1*
#124000
0*
#124500
1!
1(
b1111001 /
1*
#125000
0*
#125500
1!
0+
1)
0(
b1111010 /
1*
#126000
0*
#126500
0!
1+
0)
1(
0-
b1111011 /
1*
#127000
0*
#127500
b1111100 /
1*
#128000
0*
#128500
1)
1-
b1111101 /
1*
#129000
0*
#129500
0)
0(
b1111110 /
1*
#130000
0*
#130500
0+
1(
0-
b1111111 /
1*
#131000
0*
#131500
b10000000 /
1*
