02_sequential_basics/util.svh
`define PB(x) x
`define PD(x) x

02_sequential_basics/02_03_serial_adder_using_logic_operations_only/02_03_serial_adder_using_logic_operations_only.sv
//----------------------------------------------------------------------------
// Example
//----------------------------------------------------------------------------

module serial_adder
(
  input  clk,
  input  rst,
  input  a,
  input  b,
  output sum
);

  // Note:
  // carry_d represents the combinational data input to the carry register.

  logic carry;
  wire carry_d;

  assign { carry_d, sum } = a + b + carry;

  always_ff @ (posedge clk)
    if (rst)
      carry <= '0;
    else
      carry <= carry_d;

endmodule

//----------------------------------------------------------------------------
// Task
//----------------------------------------------------------------------------

module serial_adder_using_logic_operations_only
(
  input  clk,
  input  rst,
  input  a,
  input  b,
  output sum
);

  // Task:
  // Implement a serial adder using only ^ (XOR), | (OR), & (AND), ~ (NOT) bitwise operations.
  //
  // Notes:
  // See Harris & Harris book
  // or https://en.wikipedia.org/wiki/Adder_(electronics)#Full_adder webpage
  // for information about the 1-bit full adder implementation.
  //
  // See the testbench for the output format ($display task).

  logic carry;
  wire carry_d;

  assign { carry_d, sum } = { (a & b) | ((a ^ b) & carry), a ^ b ^ carry};

  always_ff @ (posedge clk)
    if (rst)
      carry <= '0;
    else
      carry <= carry_d;

endmodule

02_sequential_basics/02_03_serial_adder_using_logic_operations_only/testbench.sv
`include "util.svh"

module testbench;

  logic clk;

  initial
  begin
    clk = '0;

    forever
      # 500 clk = ~ clk;
  end

  logic rst;

  initial
  begin
    rst <= 'x;
    repeat (2) @ (posedge clk);
    rst <= '1;
    repeat (2) @ (posedge clk);
    rst <= '0;
  end

  logic a, b, sa_sum, actual;
  serial_adder                             sa   (.sum (sa_sum), .*);
  serial_adder_using_logic_operations_only salo (.sum (actual), .*);

  localparam n = 16;

  // Sequence of input values
  localparam [n - 1:0] seq_a        = 16'b1000_0001_1001_0010;
  localparam [n - 1:0] seq_b        = 16'b0010_0001_0101_0100;

  // Expected sequence of correct output values
  localparam [n - 1:0] seq_expected   = 16'b1010_0010_1110_0110;

  // TODO: If I misstype a variable, I just get nothing as an error?
  initial
  begin
    `ifdef __ICARUS__
      // Uncomment the following line
      // to generate a VCD file and analyze it using GTKwave or Surfer

      $dumpvars;
    `endif

    @ (negedge rst);

    for (int i = 0; i < n; i ++)
    begin
      a <= seq_a [i];
      b <= seq_b [i];

      @ (posedge clk);

      if (sa_sum !== seq_expected [i]) // Sanity Check against serial_adder
        $fatal(1, "Error: serial_adder example failed!");

      if (actual !== seq_expected [i])
        begin // TODO: If you comment the line out it just says "I give up"
        $display("FAIL %s", `__FILE__);
        $display("++ INPUT    => {%s, %s, %s}",
                 `PB(seq_a), `PB(seq_b), `PB(seq_expected));
        $display("++ TEST     => {%s, %s, %s, %s, %s}",
                 `PD(i), `PB(seq_a[i]), `PB(seq_b[i]),
                 `PB(actual), `PB(seq_expected[i]));
        $finish(1);
    end
  end

    $display ("PASS %s", `__FILE__);
    $finish;
  end

endmodule

02_sequential_basics/02_03_serial_adder_using_logic_operations_only/dump.vcd
$date
	Tue Jul 21 19:12:36 2026
$end
$version
	Icarus Verilog
$end
$timescale
	1s
$end
$scope module testbench $end
$var wire 1 ! sa_sum $end
$var wire 1 " actual $end
$var parameter 32 # n $end
$var parameter 16 $ seq_a $end
$var parameter 16 % seq_b $end
$var parameter 16 & seq_expected $end
$var reg 1 ' a $end
$var reg 1 ( b $end
$var reg 1 ) clk $end
$var reg 1 * rst $end
$scope module sa $end
$var wire 1 ' a $end
$var wire 1 ( b $end
$var wire 1 ) clk $end
$var wire 1 * rst $end
$var wire 1 ! sum $end
$var wire 1 + carry_d $end
$var reg 1 , carry $end
$upscope $end
$scope module salo $end
$var wire 1 ' a $end
$var wire 1 ( b $end
$var wire 1 ) clk $end
$var wire 1 * rst $end
$var wire 1 " sum $end
$var wire 1 - carry_d $end
$var reg 1 . carry $end
$upscope $end
$scope begin $ivl_for_loop0 $end
$var integer 32 / i [31:0] $end
$upscope $end
$upscope $end
$enddefinitions $end
$comment Show the parameter values. $end
$dumpall
b1010001011100110 &
b10000101010100 %
b1000000110010010 $
b10000 #
$end
#0
$dumpvars
b0 /
x.
x-
x,
x+
x*
0)
x(
x'
x"
x!
$end
#500
1)
#1000
0)
#1500
1*
1)
#2000
0)
#2500
0,
0.
1)
#3000
0)
#3500
0-
0"
0!
0+
0(
0'
0*
1)
#4000
0)
#4500
1"
1!
1'
b1 /
1)
#5000
0)
#5500
1(
0'
b10 /
1)
#6000
0)
#6500
0"
0!
0(
b11 /
1)
#7000
0)
#7500
1-
1+
1(
1'
b100 /
1)
#8000
0)
#8500
0-
1"
1!
0+
1,
1.
0(
0'
b101 /
1)
#9000
0)
#9500
1"
1(
0.
0,
b110 /
1)
#10000
0)
#10500
0(
1'
b111 /
1)
#11000
0)
#11500
1-
0"
0!
1+
1(
b1000 /
1)
#12000
0)
#12500
0-
1"
1!
0+
1,
1.
0(
0'
b1001 /
1)
#13000
0)
#13500
0"
0!
0.
0,
b1010 /
1)
#14000
0)
#14500
b1011 /
1)
#15000
0)
#15500
b1100 /
1)
#16000
0)
#16500
1"
1!
1(
b1101 /
1)
#17000
0)
#17500
0"
0!
0(
b1110 /
1)
#18000
0)
#18500
1"
1!
1'
b1111 /
1)
#19000
0)
#19500
b10000 /
1)
