02_sequential_basics/util.svh
`define PB(x) x
`define PD(x) x

02_sequential_basics/02_02_single_and_double_rate_fibonacci/02_02_single_and_double_rate_fibonacci.sv
//----------------------------------------------------------------------------
// Example
//----------------------------------------------------------------------------

module fibonacci
(
  input               clk,
  input               rst,
  output logic [15:0] num
);

  logic [15:0] num2;

  always_ff @ (posedge clk)
    if (rst)
      { num, num2 } <= { 16'd1, 16'd1 };
    else
      { num, num2 } <= { num2, num + num2 };

endmodule

//----------------------------------------------------------------------------
// Task
//----------------------------------------------------------------------------

module fibonacci_2
(
  input               clk,
  input               rst,
  output logic [15:0] num,
  output logic [15:0] num2
);

  // Task:
  // Implement a module that generates two fibonacci numbers per cycle

  always_ff @ (posedge clk)
    if (rst) begin
      { num, num2 } <= { 16'd1, 16'd1 };
    end else begin
      { num, num2 } <= { num + num2, num + num2 + num2 };
    end

endmodule

02_sequential_basics/02_02_single_and_double_rate_fibonacci/testbench.sv
`include "util.svh"

module testbench;

  logic clk;

  initial
  begin
    clk = 0;

    forever
      # 500 clk = ~ clk;
  end

  logic rst;

  initial
  begin
    rst <= 'x;
    repeat (2) @ (posedge clk);
    rst <= '1;
    repeat (2) @ (posedge clk);
    rst <= '0;
  end

  logic [15:0] f1_num, f2_num, f2_num2;

  fibonacci   f1 (.num (f1_num), .*);
  fibonacci_2 f2 (.num (f2_num), .num2 (f2_num2), .*);

  localparam n = 10;

  logic [15:0] fifo1 [$], fifo2 [$];

  integer     round = 1;

  initial
  begin
    `ifdef __ICARUS__
      // Uncomment the following line
      // to generate a VCD file and analyze it using GTKwave or Surfer

      $dumpvars;
    `endif

    @ (negedge rst);
    while (fifo1.size () < n)
    begin
      @ (posedge clk);

      fifo1.push_back (f1_num);
      fifo2.push_back (f2_num);
      fifo2.push_back (f2_num2);
    end

    while (fifo1.size () > 0 && fifo2.size () > 0)
    begin
      logic [15:0] expected, actual;

      expected = fifo1.pop_front ();
      actual = fifo2.pop_front ();

      if (expected !== actual)
      begin
        // TODO: We should try to get this to display as a table
        // of [ROUND | EXPECTED | ACTUAL ] for all n rounds. This
        // currently only displays the failing round.
        $display("FAIL %s", `__FILE__);
        $display("++ TEST     => {%s, %s, %s}",
                 `PD(round), `PD(expected), `PD(actual));
        $finish(1);
      end
      round += 1;
    end

    $display ("PASS %s", `__FILE__);
    $finish;
  end

endmodule

02_sequential_basics/02_02_single_and_double_rate_fibonacci/dump.vcd
$date
	Tue Jul 21 18:45:50 2026
$end
$version
	Icarus Verilog
$end
$timescale
	1s
$end
$scope module testbench $end
$var wire 16 ! f2_num2 [15:0] $end
$var wire 16 " f2_num [15:0] $end
$var wire 16 # f1_num [15:0] $end
$var parameter 32 $ n $end
$var reg 1 % clk $end
$var reg 1 & rst $end
$var integer 32 ' round [31:0] $end
$scope module f1 $end
$var wire 1 % clk $end
$var wire 1 & rst $end
$var reg 16 ( num [15:0] $end
$var reg 16 ) num2 [15:0] $end
$upscope $end
$scope module f2 $end
$var wire 1 % clk $end
$var wire 1 & rst $end
$var reg 16 * num [15:0] $end
$var reg 16 + num2 [15:0] $end
$upscope $end
$scope begin $unm_blk_5 $end
$var reg 16 , actual [15:0] $end
$var reg 16 - expected [15:0] $end
$upscope $end
$upscope $end
$enddefinitions $end
$comment Show the parameter values. $end
$dumpall
b1010 $
$end
#0
$dumpvars
bx -
bx ,
bx +
bx *
bx )
bx (
b1 '
x&
0%
bx #
bx "
bx !
$end
#500
1%
#1000
0%
#1500
1&
1%
#2000
0%
#2500
b1 #
b1 (
b1 )
b1 "
b1 *
b1 !
b1 +
1%
#3000
0%
#3500
0&
1%
#4000
0%
#4500
b10 )
b10 "
b10 *
b11 !
b11 +
1%
#5000
0%
#5500
b101 "
b101 *
b1000 !
b1000 +
b10 #
b10 (
b11 )
1%
#6000
0%
#6500
b11 #
b11 (
b101 )
b1101 "
b1101 *
b10101 !
b10101 +
1%
#7000
0%
#7500
b100010 "
b100010 *
b110111 !
b110111 +
b101 #
b101 (
b1000 )
1%
#8000
0%
#8500
b1000 #
b1000 (
b1101 )
b1011001 "
b1011001 *
b10010000 !
b10010000 +
1%
#9000
0%
#9500
b11101001 "
b11101001 *
b101111001 !
b101111001 +
b1101 #
b1101 (
b10101 )
1%
#10000
0%
#10500
b10101 #
b10101 (
b100010 )
b1001100010 "
b1001100010 *
b1111011011 !
b1111011011 +
1%
#11000
0%
#11500
b11000111101 "
b11000111101 *
b101000011000 !
b101000011000 +
b100010 #
b100010 (
b110111 )
1%
#12000
0%
#12500
b110111 #
b110111 (
b1011001 )
b1000001010101 "
b1000001010101 *
b1101001101101 !
b1101001101101 +
1%
#13000
0%
#13500
b10101011000010 "
b10101011000010 *
b100010100101111 !
b100010100101111 +
b1011001 #
b1011001 (
b10010000 )
b1011 '
b110111 ,
b110111 -
1%
